README.txt
setup.py
aliens/__init__.py
aliens/aliens.py
aliens/aliens_tests.py
aliens/behemoth_battle.py
aliens/descriptions.py
aliens/guess_game.py
aliens/lexicon.py
aliens/sneak.py
zorky.egg-info/PKG-INFO
zorky.egg-info/SOURCES.txt
zorky.egg-info/dependency_links.txt
zorky.egg-info/requires.txt
zorky.egg-info/top_level.txt