Metadata-Version: 1.0
Name: zorky
Version: 2.0
Summary: Text based adventure game
Home-page: UNKNOWN
Author: Jose Luis Naranjo Gomez
Author-email: luisnaranjo733@hotmail.com
License: UNKNOWN
Platform: UNKNOWN
